rickled/__init__.py
tests/integration/__init__.py
tests/unittest/__init__.py
tests/unittest/test_object_rickler.py
tests/unittest/test_rickle.py
gsrickled-1.0.0.dist-info/LICENSE
gsrickled-1.0.0.dist-info/METADATA
gsrickled-1.0.0.dist-info/WHEEL
gsrickled-1.0.0.dist-info/top_level.txt
gsrickled-1.0.0.dist-info/RECORD
