Metadata-Version: 2.1
Name: gsrickled
Version: 1.0.0
Summary: Tools for pickling Python objects in completely different way
Home-page: UNKNOWN
Author: Zipfian Science, Fabian Sperrle
Author-email: fabian.sperrle@uni-konstanz.de
License: Apache 2.0
Keywords: Pickle,Python
Platform: UNKNOWN
Classifier: Intended Audience :: Science/Research
Classifier: Operating System :: OS Independent
Classifier: Programming Language :: Python :: 3
Classifier: Topic :: Scientific/Engineering :: Artificial Intelligence
License-File: LICENSE
Requires-Dist: pyyaml
Requires-Dist: requests
